skyroom.py
skyroom-1.0.3.dist-info/LICENSE
skyroom-1.0.3.dist-info/METADATA
skyroom-1.0.3.dist-info/WHEEL
skyroom-1.0.3.dist-info/top_level.txt
skyroom-1.0.3.dist-info/RECORD
