Metadata-Version: 2.1
Name: skyroom
Version: 1.0.3
Summary: Skyroom Python library
Home-page: https://github.com/AriaMoradi/skyroom-python
Author: Aria Moradi
Author-email: aria.moradi007@gmail.com
License: UNKNOWN
Keywords: skyroom,api
Platform: UNKNOWN
Classifier: Programming Language :: Python
Classifier: Operating System :: OS Independent
Classifier: License :: OSI Approved :: MIT License
Classifier: Intended Audience :: Developers
Classifier: Development Status :: 5 - Production/Stable
Classifier: Topic :: Software Development :: Libraries :: Python Modules
Classifier: Topic :: Communications :: Conferencing
Requires-Dist: requests (>=2.22.0)
